mcp_software_company/__init__.py
mcp_software_company/__main__.py
mcp_software_company/server.py
mcp_software_company/logs/20250818.txt
mcp_software_company/metagpt/tools/schemas/CatCount.yml
mcp_software_company/metagpt/tools/schemas/CatCross.yml
mcp_software_company/metagpt/tools/schemas/FillMissingValue.yml
mcp_software_company/metagpt/tools/schemas/GPTvGenerator.yml
mcp_software_company/metagpt/tools/schemas/GeneralSelection.yml
mcp_software_company/metagpt/tools/schemas/GroupStat.yml
mcp_software_company/metagpt/tools/schemas/KFoldTargetMeanEncoder.yml
mcp_software_company/metagpt/tools/schemas/LabelEncode.yml
mcp_software_company/metagpt/tools/schemas/MaxAbsScale.yml
mcp_software_company/metagpt/tools/schemas/MinMaxScale.yml
mcp_software_company/metagpt/tools/schemas/OneHotEncode.yml
mcp_software_company/metagpt/tools/schemas/OrdinalEncode.yml
mcp_software_company/metagpt/tools/schemas/PolynomialExpansion.yml
mcp_software_company/metagpt/tools/schemas/RobustScale.yml
mcp_software_company/metagpt/tools/schemas/SDEngine.yml
mcp_software_company/metagpt/tools/schemas/SplitBins.yml
mcp_software_company/metagpt/tools/schemas/StandardScale.yml
mcp_software_company/metagpt/tools/schemas/TargetMeanEncoder.yml
mcp_software_company/metagpt/tools/schemas/VarianceBasedSelection.yml
mcp_software_company/metagpt/tools/schemas/email_login_imap.yml
mcp_software_company/metagpt/tools/schemas/scrape_web_playwright.yml
mcp_software_company-0.1.1.dist-info/METADATA
mcp_software_company-0.1.1.dist-info/WHEEL
mcp_software_company-0.1.1.dist-info/entry_points.txt
mcp_software_company-0.1.1.dist-info/RECORD
